reflectsonar/__init__.py
reflectsonar/__main__.py
reflectsonar/main.py
reflectsonar/api/__init__.py
reflectsonar/api/get_data.py
reflectsonar/data/__init__.py
reflectsonar/data/models.py
reflectsonar/report/__init__.py
reflectsonar/report/cover_page.py
reflectsonar/report/hotspots.py
reflectsonar/report/issues.py
reflectsonar/report/pdfgen.py
reflectsonar/report/reflect-sonar.png
reflectsonar/report/rules.py
reflectsonar/report/utils.py
reflectsonar-1.0.1.dist-info/licenses/LICENSE
reflectsonar-1.0.1.dist-info/METADATA
reflectsonar-1.0.1.dist-info/WHEEL
reflectsonar-1.0.1.dist-info/entry_points.txt
reflectsonar-1.0.1.dist-info/top_level.txt
reflectsonar-1.0.1.dist-info/RECORD
