Metadata-Version: 2.4
Name: reflectsonar
Version: 1.0.1
Summary: PDF Report Generator for SonarQube Analysis
Author-email: Ata Seren <ata.seren@hotmail.com>
License-Expression: GPL-3.0-or-later
Project-URL: Homepage, https://github.com/ataseren/reflectsonar
Project-URL: Repository, https://github.com/ataseren/reflectsonar
Project-URL: Issues, https://github.com/ataseren/reflectsonar/issues
Keywords: sonarqube,quality,report,pdf,analysis,code-quality
Classifier: Development Status :: 5 - Production/Stable
Classifier: Intended Audience :: Developers
Classifier: Topic :: Software Development :: Quality Assurance
Classifier: Topic :: Software Development :: Testing
Classifier: Programming Language :: Python :: 3
Classifier: Programming Language :: Python :: 3.8
Classifier: Programming Language :: Python :: 3.9
Classifier: Programming Language :: Python :: 3.10
Classifier: Programming Language :: Python :: 3.11
Classifier: Programming Language :: Python :: 3.12
Classifier: Operating System :: OS Independent
Classifier: Environment :: Console
Requires-Python: >=3.8
License-File: LICENSE
Requires-Dist: certifi>=2023.0.0
Requires-Dist: chardet>=5.0.0
Requires-Dist: charset-normalizer>=3.0.0
Requires-Dist: idna>=3.0
Requires-Dist: pillow>=10.0.0
Requires-Dist: reportlab>=4.0.0
Requires-Dist: requests>=2.28.0
Requires-Dist: urllib3>=2.0.0
Requires-Dist: pyyaml>=6.0.0
Provides-Extra: dev
Requires-Dist: pytest>=7.0.0; extra == "dev"
Requires-Dist: pytest-cov>=4.0.0; extra == "dev"
Requires-Dist: black>=23.0.0; extra == "dev"
Requires-Dist: flake8>=6.0.0; extra == "dev"
Requires-Dist: pylint>=2.17.0; extra == "dev"
Requires-Dist: mypy>=1.0.0; extra == "dev"
Requires-Dist: build>=0.10.0; extra == "dev"
Requires-Dist: twine>=4.0.0; extra == "dev"
Dynamic: license-file
